{
    "faction": "/r/omori",
    "contact": "omocord",
    "notifications": "?????",
    "templates": [
        {
            "name": "OMORI Portrait",
            "sources": [
                "https://raw.githubusercontent.com/sunryze-git/omoriplace2023/main/second.png"
            ],
            "x": 500,
            "y": 500
        }
    ],
    "whitelist": [
        {
            "name": "r/hatsune",
            "url": "https://hatsune.proxnet.dev/place/overlayRaw"
        }
    ],
    "blacklist": [
        {
            "name": "r/omori",
            "url": "https://raw.githubusercontent.com/sunryze-git/omoriplace2023/main/omoriplace.json"
        }
    ]
}
